ekca_client/__about__.py
ekca_client/__init__.py
ekca_client/cfg.py
ekca_client/cmd.py
ekca_client/req.py
ekca_client/sshinit.py
ekca_client/__pycache__/__about__.cpython-38.opt-1.pyc
ekca_client/__pycache__/__init__.cpython-38.opt-1.pyc
ekca_client/__pycache__/cfg.cpython-38.opt-1.pyc
ekca_client/__pycache__/cmd.cpython-38.opt-1.pyc
ekca_client/__pycache__/req.cpython-38.opt-1.pyc
ekca_client/__pycache__/sshinit.cpython-38.opt-1.pyc
ekca_client-1.0.1.dist-info/LICENSE
ekca_client-1.0.1.dist-info/METADATA
ekca_client-1.0.1.dist-info/WHEEL
ekca_client-1.0.1.dist-info/entry_points.txt
ekca_client-1.0.1.dist-info/top_level.txt
ekca_client-1.0.1.dist-info/RECORD
